{
    "version": "5.1.1",
    "description": "Pester is a test and mock framework for PowerShell.",
    "homepage": "https://pester.dev/",
    "license": "Apache-2.0",
    "url": "https://www.powershellgallery.com/api/v2/package/Pester/5.1.1#/dl.nupkg",
    "hash": "926b92ca08014fe095e65f7c42646364a8ebc4558c33b6c80b8f86d26eebf3dd",
    "psmodule": {
        "name": "Pester"
    },
    "checkver": {
        "github": "https://github.com/pester/Pester"
    },
    "autoupdate": {
        "url": "https://www.powershellgallery.com/api/v2/package/Pester/$version#/dl.nupkg"
    }
}
